olx/__init__.py
olx/category.py
olx/offer.py
olx/utils.py
pyolx-0.0.3.dist-info/DESCRIPTION.rst
pyolx-0.0.3.dist-info/METADATA
pyolx-0.0.3.dist-info/RECORD
pyolx-0.0.3.dist-info/WHEEL
pyolx-0.0.3.dist-info/metadata.json
pyolx-0.0.3.dist-info/top_level.txt
