Metadata-Version: 2.0
Name: pyolx
Version: 0.0.3
Summary: pyolx - python wrapper for olx
Home-page: https://github.com/limebrains/pyolx
Author: LimeBrains
Author-email: mail@limebrains.com
License: UNKNOWN
Platform: UNKNOWN
